setup.py
neez/__init__.py
neez.egg-info/PKG-INFO
neez.egg-info/SOURCES.txt
neez.egg-info/dependency_links.txt
neez.egg-info/not-zip-safe
neez.egg-info/top_level.txt