Metadata-Version: 1.0
Name: neez
Version: 0.1
Summary: chff short message client
Home-page: http://github.com/mnes-io/neez
Author: Charles Perkins
Author-email: charlesap@gmail.com
License: MIT
Platform: UNKNOWN
